[
  {
    "DRGID": 1,
    "Datum": "04.08.2025",
    "HerzkatheterID": 3,
    "Herzteam": 1,
    "Materialpreis": 0.0,
    "PatientID": 12379,
    "Roentgen": 1,
    "UntersucherAbrechnungID": 12,
    "UntersuchungID": 17777,
    "UntersuchungartID": 1,
    "ZuweiserID": 43
  },
  {
    "DRGID": 1,
    "Datum": "04.08.2025",
    "HerzkatheterID": 3,
    "Herzteam": 1,
    "Materialpreis": 0.0,
    "PatientID": 12413,
    "Roentgen": 1,
    "UntersucherAbrechnungID": 12,
    "UntersuchungID": 17778,
    "UntersuchungartID": 1,
    "ZuweiserID": 43
  },
  {
    "DRGID": 1,
    "Datum": "04.08.2025",
    "HerzkatheterID": 3,
    "Herzteam": 1,
    "Materialpreis": 0.0,
    "PatientID": 12870,
    "Roentgen": 1,
    "UntersucherAbrechnungID": 12,
    "UntersuchungID": 17779,
    "UntersuchungartID": 1,
    "ZuweiserID": 26
  },
  {
    "DRGID": 1,
    "Datum": "04.08.2025",
    "HerzkatheterID": 3,
    "Herzteam": 1,
    "Materialpreis": 0.0,
    "PatientID": 12871,
    "Roentgen": 1,
    "UntersucherAbrechnungID": 12,
    "UntersuchungID": 17780,
    "UntersuchungartID": 1,
    "ZuweiserID": 26
  },
  {
    "DRGID": 1,
    "Datum": "04.08.2025",
    "HerzkatheterID": 3,
    "Herzteam": 1,
    "Materialpreis": 0.0,
    "PatientID": 12872,
    "Roentgen": 1,
    "UntersucherAbrechnungID": 12,
    "UntersuchungID": 17781,
    "UntersuchungartID": 1,
    "ZuweiserID": 26
  },
  {
    "DRGID": 1,
    "Datum": "04.08.2025",
    "HerzkatheterID": 3,
    "Herzteam": 1,
    "Materialpreis": 0.0,
    "PatientID": 12873,
    "Roentgen": 1,
    "UntersucherAbrechnungID": 12,
    "UntersuchungID": 17782,
    "UntersuchungartID": 1,
    "ZuweiserID": 26
  },
  {
    "DRGID": 1,
    "Datum": "04.08.2025",
    "HerzkatheterID": 3,
    "Herzteam": 1,
    "Materialpreis": 0.0,
    "PatientID": 12874,
    "Roentgen": 1,
    "UntersucherAbrechnungID": 12,
    "UntersuchungID": 17783,
    "UntersuchungartID": 1,
    "ZuweiserID": 26
  },
  {
    "DRGID": 1,
    "Datum": "04.08.2025",
    "HerzkatheterID": 3,
    "Herzteam": 1,
    "Materialpreis": 0.0,
    "PatientID": 12878,
    "Roentgen": 1,
    "UntersucherAbrechnungID": 12,
    "UntersuchungID": 17788,
    "UntersuchungartID": 1,
    "ZuweiserID": 26
  },
  {
    "DRGID": 1,
    "Datum": "04.08.2025",
    "HerzkatheterID": 3,
    "Herzteam": 1,
    "Materialpreis": 0.0,
    "PatientID": 12879,
    "Roentgen": 1,
    "UntersucherAbrechnungID": 12,
    "UntersuchungID": 17789,
    "UntersuchungartID": 1,
    "ZuweiserID": 26
  },
  {
    "DRGID": 1,
    "Datum": "04.08.2025",
    "HerzkatheterID": 3,
    "Herzteam": 1,
    "Materialpreis": 0.0,
    "PatientID": 12880,
    "Roentgen": 1,
    "UntersucherAbrechnungID": 12,
    "UntersuchungID": 17790,
    "UntersuchungartID": 1,
    "ZuweiserID": 26
  }
]